{"id":"13d7c388ecb2","slug":"lines-on-startling-a-rabbit-13d7c388ecb2","title":"Lines, on Startling a Rabbit.","content":"    Whew! - Tha'rt in a famous hurry!\r\n    Awm nooan baan to try to catch thi!\r\n    Aw've noa dogs wi' me to worry\r\n    Thee poor thing, - aw like to watch thi.\r\n    Tha'rt a runner! aw dar back thi,\r\n    Why, tha ommost seems to fly!\r\n    Did ta think aw meant to tak thi?\r\n    Well, awm fond o' rabbit pie.\n\r\n    Aw dooan't want th' world to misen, mun,\r\n    Awm nooan like a dog i'th' manger;\r\n    Yet still 'twor happen best to run,\r\n    For tha'rt th' safest aght o' danger.\r\n    An sometimes fowks' inclination\r\n    Leads 'em to do what they shouldn't; - \r\n    But tha's saved me a temptation, - \r\n    Aw've net harmed thi, 'coss aw couldn't.\n\r\n    Aw wish all temptations fled me,\r\n    As tha's fled throo me to-day;\r\n    For they've oft to trouble led me,\r\n    For which aw've had dear to pay.\r\n    An a taicher wise aw've faand thi,\r\n    An this lesson gained throo thee;\r\n    'At when dangers gether raand me,\r\n    Th' wisest tactics is to flee.\n\r\n    They may call thi coward, Bunny,\r\n    But if mine had been thy lot,\r\n    Aw should fail to see owt funny,\r\n    To be stewin in a pot.\r\n    Life to thee, awm sewer is sweeter,\r\n    Nor thi flesh to me could prove;\r\n    May thy lot an mine grow breeter,\r\n    Blest wi' liberty an love.","writer":"John Hartley","category":["classic"],"meaning":"\"Lines, on Startling a Rabbit.\" is a quintessential example of John Hartley's signature style...\n\n### Why We Love This Line\nAt Linespedia, we believe that poetry is the ultimate sanctuary for the soul...","meta":{"views":1290,"dates":"1839-1915"}}