{"id":"32354dd19612","slug":"oconnells-statue-32354dd19612","title":"O'Connell's Statue.","content":"Lines To Hogan.\n\n\r\n    Chisel the likeness of The Chief,\r\n    Not in gaiety, nor grief;\r\n    Change not by your art to stone,\r\n    Ireland's laugh, or Ireland's moan.\r\n    Dark her tale, and none can tell\r\n    Its fearful chronicle so well.\r\n    Her frame is bent--her wounds are deep--\r\n    Who, like him, her woes can weep?\n\r\n    He can be gentle as a bride,\r\n    While none can rule with kinglier pride;\r\n    Calm to hear, and wise to prove,\r\n    Yet gay as lark in soaring love.\r\n    Well it were, posterity\r\n    Should have some image of his glee;\r\n    That easy humour, blossoming\r\n    Like the thousand flowers of spring!\r\n    Glorious the marble which could show\r\n    His bursting sympathy for woe:\r\n    Could catch the pathos, flowing wild,\r\n    Like mother's milk to craving child.\n\r\n    And oh! how princely were the art\r\n    Could mould his mien, or tell his heart\r\n    When sitting sole on Tara's hill,\r\n    While hung a million on his will!\r\n    Yet, not in gaiety, nor grief,\r\n    Chisel the image of our Chief,\r\n    Nor even in that haughty hour\r\n    When a nation owned his power.\n\r\n    But would you by your art unroll\r\n    His own, and Ireland's secret soul,\r\n    And give to other times to scan\r\n    The greatest greatness of the man?\r\n    Fierce defiance let him be\r\n    Hurling at our enemy--\r\n    From a base as fair and sure\r\n    As our love is true and pure;\r\n    Let his statue rise as tall\r\n    And firm as a castle wall;\r\n    On his broad brow let there be\r\n    A type of Ireland's history;\r\n    Pious, generous, deep and warm,\r\n    Strong and changeful as a storm;\r\n    Let whole centuries of wrong\r\n    Upon his recollection throng--\r\n    Strongbow's force, and Henry's wile,\r\n    Tudor's wrath, and Stuart's guile,\r\n    And iron Strafford's tiger jaws,\r\n    And brutal Brunswick's penal laws;\r\n    Not forgetting Saxon faith,\r\n    Not forgetting Norman scath,\r\n    Not forgetting William's word,\r\n    Not forgetting Cromwell's sword.\r\n    Let the Union's fetter vile--\r\n    The shame and ruin of our isle--\r\n    Let the blood of 'Ninety-Eight\r\n    And our present blighting fate--\r\n    Let the poor mechanic's lot,\r\n    And the peasant's ruined cot,\r\n    Plundered wealth and glory flown,\r\n    Ancient honours overthrown--\r\n    Let trampled altar, rifled urn,\r\n    Knit his look to purpose stern.\n\r\n    Mould all this into one thought,\r\n    Like wizard cloud with thunder fraught;\r\n    Still let our glories through it gleam,\r\n    Like fair flowers through a flooded stream,\r\n    Or like a flashing wave at night,\r\n    Bright,--'mid the solemn darkness, bright.\r\n    Let the memory of old days\r\n    Shine through the statesman's anxious face--\r\n    Dathi's power, and Brian's fame,\r\n    And headlong Sarsfield's sword of flame;\r\n    And the spirit of Red Hugh,\r\n    And the pride of 'Eighty-Two,\r\n    And the victories he won,\r\n    And the hope that leads him on!\n\r\n    Let whole armies seem to fly\r\n    From his threatening hand and eye.\r\n    Be the strength of all the land\r\n    Like a falchion in his hand,\r\n    And be his gesture sternly grand.\r\n    A braggart tyrant swore to smite\r\n    A people struggling for their right;\r\n    O'Connell dared him to the field,\r\n    Content to die but never yield;\r\n    Fancy such a soul as his,\r\n    In a moment such as this,\r\n    Like cataract, or foaming tide,\r\n    Or army charging in its pride.\r\n    Thus he spoke, and thus he stood,\r\n    Proffering in our cause his blood.\r\n    Thus his country loves him best--\r\n    To image this is your behest.\r\n    Chisel thus, and thus alone,\r\n    If to man you'd change the stone.","writer":"Thomas Osborne Davis","category":["classic"],"meaning":"Thomas Osborne Davis's contribution to classic is further solidified by the brilliance found in \"O'Connell's Statue.\"...\n\n### Why We Love This Line\nAt Linespedia, we believe that poetry is the ultimate sanctuary for the soul...","meta":{"views":1096,"dates":"October 14, 1814 - September 16, 1845"}}