{"id":"387de71ac172","slug":"drouth-387de71ac172","title":"Drouth","content":"I\n\r\n    The hot sunflowers by the glaring pike\r\n    Lift shields of sultry brass; the teasel tops,\r\n    Pink-thorned, advance with bristling spike on spike\r\n    Against the furious sunlight. Field and copse\r\n    Are sick with summer: now, with breathless stops,\r\n    The locusts cymbal; now grasshoppers beat\r\n    Their castanets: and rolled in dust, a team, - \r\n    Like some mean life wrapped in its sorry dream, - \r\n    An empty wagon rattles through the heat.\n\r\nII\n\r\n    Where now the blue wild iris? flowers whose mouths\r\n    Are moist and musky? Where the sweet-breathed mint,\r\n    That made the brook-bank herby? Where the South's\r\n    Wild morning-glories, rich in hues, that hint\r\n    At coming showers that the rainbows tint?\r\n    Where all the blossoms that the wildwood knows?\r\n    The frail oxalis hidden in its leaves;\r\n    The Indian-pipe, pale as a soul that grieves;\r\n    The freckled touch-me-not and forest rose.\n\r\nIII\n\r\n    Dead! dead! all dead beside the drouth-burnt brook,\r\n    Shrouded in moss or in the shriveled grass.\r\n    Where waved their bells, from which the wild-bee shook\r\n    The dewdrop once, - gaunt, in a nightmare mass,\r\n    The rank weeds crowd; through which the cattle pass,\r\n    Thirsty and lean, seeking some meager spring,\r\n    Closed in with thorns, on which stray bits of wool\r\n    The panting sheep have left, that sought the cool,\r\n    From morn till evening wearily wandering.\n\r\nIV\n\r\n    No bird is heard; no throat to whistle awake\r\n    The sleepy hush; to let its music leak\r\n    Fresh, bubble-like, through bloom-roofs of the brake:\r\n    Only the green-gray heron, famine-weak, - \r\n    Searching the stale pools of the minnowless creek, - \r\n    Utters its call; and then the rain-crow, too,\r\n    False prophet now, croaks to the stagnant air;\r\n    While overhead, - still as if painted there, - \r\n    A buzzard hangs, black on the burning blue.","writer":"Madison Julius Cawein","category":["classic"],"meaning":"Madison Julius Cawein's contribution to classic is further solidified by the brilliance found in \"Drouth\"...\n\n### Why We Love This Line\nAt Linespedia, we believe that poetry is the ultimate sanctuary for the soul...","meta":{"views":1333,"dates":"23 March 1865 - 8 December 1914"}}