{"id":"49e57dfa3ab6","slug":"an-easter-flower-49e57dfa3ab6","title":"An Easter Flower.","content":"I.\n\r\n    The flower that she gave to me\r\n        Has withered now and died--\r\n    But yet with fond fidelity\r\n        Its faded leaves abide.\n\n\r\nII.\n\r\n    The petals that so fragrant then\r\n        She wore upon her breast--\r\n    Still clinging to the lifeless stem,\r\n        With miser care possessed.\n\n\r\nIII.\n\r\n    As when in sweetest purity\r\n        It shed its perfume rare,\r\n    A symbol dear 'twill ever be\r\n        Of one divinely fair!\n\n\r\nIV.\n\r\n    Plucked by the cruel hand of Death\r\n        In beauty's youthful bloom--\r\n    She perished with his chilling breath,\r\n        And withered in the tomb.\n\n\r\nV.\n\r\n    But I will cherish ever thus\r\n        The token that she gave\r\n    When sun-lit skies were over us,\r\n        Unclouded by the grave!","writer":"George W. Doneghy","category":["classic"],"meaning":"\"An Easter Flower.\" is a quintessential example of George W. Doneghy's signature style...\n\n### Why We Love This Line\nAt Linespedia, we believe that poetry is the ultimate sanctuary for the soul...","meta":{"views":1307,"dates":null}}