{"id":"54f0d912ad17","slug":"to-a-musquito-54f0d912ad17","title":"To A Musquito.","content":"    Fair insect! that, with threadlike legs spread out,\r\n    And blood-extracting bill and filmy wing,\r\n    Does murmur, as thou slowly sail'st about,\r\n    In pitiless ears full many a plaintive thing,\r\n    And tell how little our large veins should bleed,\r\n    Would we but yield them to thy bitter need.\n\r\n    Unwillingly, I own, and, what is worse,\r\n    Full angrily men hearken to thy plaint;\r\n    Thou gettest many a brush, and many a curse,\r\n    For saying thou art gaunt, and starved, and faint:\r\n    Even the old beggar, while he asks for food,\r\n    Would kill thee, hapless stranger, if he could.\n\r\n    I call thee stranger, for the town, I ween,\r\n    Has not the honour of so proud a birth,\r\n    Thou com'st from Jersey meadows, fresh and green,\r\n    The offspring of the gods, though born on earth;\r\n    For Titan was thy sire, and fair was she,\r\n    The ocean nymph that nursed thy infancy.\n\r\n    Beneath the rushes was thy cradle swung,\r\n    And when, at length, thy gauzy wings grew strong,\r\n    Abroad to gentle airs their folds were flung,\r\n    Rose in the sky and bore thee soft along;\r\n    The south wind breathed to waft thee on thy way,\r\n    And danced and shone beneath the billowy bay.\n\r\n    Calm rose afar the city spires, and thence\r\n    Came the deep murmur of its throng of men,\r\n    And as its grateful odours met thy sense,\r\n    They seemed the perfumes of thy native fen.\r\n    Fair lay its crowded streets, and at the sight\r\n    Thy tiny song grew shriller with delight.\n\r\n    At length thy pinions fluttered in Broadway,\r\n    Ah, there were fairy steps, and white necks kissed\r\n    By wanton airs, and eyes whose killing ray\r\n    Shone through the snowy veils like stars through mist;\r\n    And fresh as morn, on many a cheek and chin,\r\n    Bloomed the bright blood through the transparent skin.\n\r\n    Sure these were sights to touch an anchorite!\r\n    What! do I hear thy slender voice complain?\r\n    Thou wailest, when I talk of beauty's light,\r\n    As if it brought the memory of pain:\r\n    Thou art a wayward being, well, come near,\r\n    And pour thy tale of sorrow in my ear.\n\r\n    What sayst thou, slanderer! rouge makes thee sick?\r\n    And China bloom at best is sorry food?\r\n    And Rowland's Kalydor, if laid on thick,\r\n    Poisons the thirsty wretch that bores for blood?\r\n    Go! 'twas a just reward that met thy crime,\r\n    But shun the sacrilege another time.\n\r\n    That bloom was made to look at, not to touch;\r\n    To worship, not approach, that radiant white;\r\n    And well might sudden vengeance light on such\r\n    As dared, like thee, most impiously to bite.\r\n    Thou shouldst have gazed at distance and admired,\r\n    Murmured thy adoration and retired.\n\r\n    Thou'rt welcome to the town, but why come here\r\n    To bleed a brother poet, gaunt like thee?\r\n    Alas! the little blood I have is dear,\r\n    And thin will be the banquet drawn from me.\r\n    Look round, the pale-eyed sisters in my cell,\r\n    Thy old acquaintance, Song and Famine, dwell.\n\r\n    Try some plump alderman, and suck the blood\r\n    Enriched by generous wine and costly meat;\r\n    On well-filled skins, sleek as thy native mud,\r\n    Fix thy light pump and press thy freckled feet:\r\n    Go to the men for whom, in ocean's hall,\r\n    The oyster breeds, and the green turtle sprawls.\n\r\n    There corks are drawn, and the red vintage flows\r\n    To fill the swelling veins for thee, and now\r\n    The ruddy cheek and now the ruddier nose\r\n    Shall tempt thee, as thou flittest round the brow;\r\n    And when the hour of sleep its quiet brings,\r\n    No angry hand shall rise to brush thy wings.","writer":"William Cullen Bryant","category":["classic"],"meaning":"Exploring the themes of classic, William Cullen Bryant delivers a powerful performance in \"To A Musquito.\"...\n\n### Why We Love This Line\nAt Linespedia, we believe that poetry is the ultimate sanctuary for the soul...","meta":{"views":1436,"dates":"November 3, 1794 - June 12, 1878"}}