{"id":"57947383fb13","slug":"spring-57947383fb13","title":"Spring","content":"    A certain Rudolf called out:\r\n    I have eaten too much.\r\n    Whether it's healthy is very questionable.\r\n    After such a greasy lunch\r\n    I really feel uncomfortable.\r\n    But I belch beautifully and smoke\r\n    Cigarettes now and then.\r\n    Lying on my heavy belly,\r\n    I chirp nothing but songs of spring.\r\n    Longingly, as though on a ramp\r\n    The voice squeals from the throat.\r\n    And like an old lamp\r\n    The wind blackens the bitter soul.","writer":"Alfred Lichtenstein","category":["classic"],"meaning":"This evocative piece by Alfred Lichtenstein, titled \"Spring\", represents a masterful exploration of classic. The lines capture a profound emotional resonance...\n\n### Why We Love This Line\nAt Linespedia, we believe that poetry is the ultimate sanctuary for the soul...","meta":{"views":1559,"dates":"23rd August 1889 - 25th September 1914"}}