{"id":"5e086d851a07","slug":"the-two-lamplighters-5e086d851a07","title":"The Two Lamplighters","content":"    I niver thowt when I grew owd\r\n         I'd tak to leetin' lamps;\r\n    I sud have said, I'd rayther pad\r\n         My hoof on t' road wi' tramps.\r\n    But sin I gate that skelp(1) i' t' mine,\r\n         I'm wankle(2) i' my heead;\r\n    So gaffer said, I'd give ower wark\r\n         An' leet town lamps atsteead.\n\r\n    At first, when I were liggin' snug\r\n         I' bed, warm as a bee,\r\n    'T were hard to rise and get agate\r\n         As sooin as t' clock strake three.\r\n    An' I were flaid to hear my steps\r\n         Echoin' on ivery wall;\r\n    An' flaider yet when down by t' church\r\n         Ullets would skreek and call.\n\r\n    But now I'm flaid o' nowt; I love\r\n         All unkerd(3) sounds o' t' neet,\r\n    Frae childer talkin' i' their dreams\r\n         To t' tramp o' p'licemen' feet.\r\n    But most of all I love to hark\r\n         To t' song o' t' birds at dawn;\r\n    They wakken up afore it gloams,\r\n         When t' dew ligs thick on t' lawn.\n\r\n    If I feel lonesome, up I look\r\n         To t' sky aboon my heead;\r\n    An' theer's yon stars all glestrin' breet,\r\n         Like daisies in a mead.\r\n    But sometimes, when I'm glowerin' up,\r\n         I see the Lord hissen;\r\n    He's doutin' all yon lamps o' Heaven\r\n         That shines on mortal men.\n\r\n    He lowps alang frae star to star,\r\n         As cobby(4) as can be;\r\n    Mebbe He reckons fowk's asleep,\r\n         Wi' niver an eye to see.\r\n    But I hae catched Him at his wark,\r\n         For all He maks no din;\r\n    He leaves a track o' powder'd gowd(5)\r\n         To show where He has bin.\n\r\n    He's got big lamps an' laatle lamps,\r\n         An' lamps that twinkles red;\r\n    Im capped to see Him dout 'em all\r\n         Afore I'm back i' bed.\r\n    But He don't laik about His wark,\r\n         Or stop to hark to t' birds;\r\n    He minds His business, does the Lord,\r\n         An' wastes no gaumless words.\n\r\n    I grow more like Him ivery day,\r\n         For all I walk so lame;\r\n    An', happen, there will coom a time\r\n         I'll beat Him at His game.\r\n    Thrang as Throp's wife, I'll dout my lamps\r\n         Afore He's gotten so far;\r\n    An' then I'll shout--\"I've won my race,\r\n         I've bet Him by a star.\"","writer":"Frederic William Moorman","category":["classic"],"meaning":"\"The Two Lamplighters\" is a quintessential example of Frederic William Moorman's signature style...\n\n### Why We Love This Line\nAt Linespedia, we believe that poetry is the ultimate sanctuary for the soul...","meta":{"views":1127,"dates":"1872 - 1919"}}