{"id":"6459be72754f","slug":"forgiven-6459be72754f","title":"Forgiven.","content":"    I might have met his anger with a smile\r\n        For so it was that I had set my heart\r\n    To mask deception with a wanton's guile,\r\n        And save the tears that now begin to start.\n\r\n    I might have worn my guilty crown of thorn,--\r\n        Yea, even worn it gladly like a prize;\r\n    But, oh! more bitter than his rage or scorn,\r\n        He left me with forgiveness in his eyes.","writer":"Charles Hamilton Musgrove","category":["classic"],"meaning":"Charles Hamilton Musgrove's contribution to classic is further solidified by the brilliance found in \"Forgiven.\"...\n\n### Why We Love This Line\nAt Linespedia, we believe that poetry is the ultimate sanctuary for the soul...","meta":{"views":1472,"dates":null}}