{"id":"663dad44d8fa","slug":"another-grace-for-a-child-663dad44d8fa","title":"Another Grace For A Child","content":"Here a little child I stand\r\nHeaving up my either hand;\r\nCold as paddocks though they be,\r\nHere I lift them up to Thee,\r\nFor a benison to fall\r\nOn our meat, and on us all. Amen.\n","writer":"Robert Herrick","category":["classic"],"meaning":"Exploring the themes of classic, Robert Herrick delivers a powerful performance in \"Another Grace For A Child\"...\n\n### Why We Love This Line\nAt Linespedia, we believe that poetry is the ultimate sanctuary for the soul...","meta":{"views":2349,"dates":"Baptized - August 24, 1591- October 1674"}}