{"id":"8a215e636594","slug":"st-ignatius-loyola-at-the-chapel-of-our-lady-of-montserrat-8a215e636594","title":"St. Ignatius Loyola At The Chapel Of Our Lady Of Montserrat.","content":"    'Tis midnight, and solemn darkness broods\r\n        In a lonely, sacred fane - \r\n    The church of Our Lady of Montserrat,\r\n        So famous throughout all Spain;\r\n    For countless were the pilgrim hosts\r\n        Who knelt at that sacred shrine\r\n    With aching hearts, that came to seek\r\n        Relief and grace divine.\n\r\n    Pure as the light of the evening star\r\n        Shines the lamp's pale, solemn ray,\r\n    That burns through midnight's hush and gloom,\r\n        As well as the glare of day,\r\n    Like the Christian soul, enwrapped in God,\r\n        Resigning each vain delight,\r\n    Each earthly lure, to burn and shine\r\n        With pure love in His sight.\n\r\n    Softly the gentle radiance falls\r\n        On a mail-clad warrior there,\r\n    Who humbly bows his stately head\r\n        In silent, earnest prayer;\r\n    It flashes back from his corslet bright,\r\n        From each shining steel clad hand,\r\n    And the brow which tells that he was born\r\n        To pomp and high command.\n\r\n    Say, who is he, that vigil keeps,\r\n        Like the warrior knights of old,\r\n    Through the long lone hours of the silent night,\r\n        Ere they donned their spurs of gold?\r\n    A soldier brave and proud is he,\r\n        And bears a noble name,\r\n    Since Pampeluna's glorious day\r\n        Won Loyola his fame.\n\r\n    What doth he at this lowly shrine?\r\n        What mean those prayers and sighs,\r\n    The tearful mist that dims the light\r\n        Of his flashing, eagle eyes?\r\n    They tell of life's vain pomps and pride\r\n        Esteemed as worthless dross,\r\n    For the dauntless soldier has become\r\n        The soldier of the Cross.\n\r\n    That sword, that once like lightning swept\r\n        Through ranks of foes hard pressed,\r\n    Now hangs beside Our Lady's shrine,\r\n        Henceforth in peace to rest, - \r\n    And soon the penitent's rough, dark robe,\r\n        His girdle and cowl of gloom,\r\n    Will replace the soldier's armor bright,\r\n        And his lofty, waving plume.\n\r\n    Well done, well done, thou warrior brave!\r\n        A noble choice is thine!\r\n    What are the laurels of earth beside\r\n        The joys of bliss divine?\r\n    And thou hast won, though seeking not,\r\n        The saint's undying fame - \r\n    Christ's Holy Church will evermore\r\n        Revere and bless thy name!","writer":"Rosanna Eleanor Leprohon","category":["classic"],"meaning":"This evocative piece by Rosanna Eleanor Leprohon, titled \"St. Ignatius Loyola At The Chapel Of Our Lady Of Montserrat.\", represents a masterful exploration of classic. The lines capture a profound emotional resonance...\n\n### Why We Love This Line\nAt Linespedia, we believe that poetry is the ultimate sanctuary for the soul...","meta":{"views":1003,"dates":"1832 - 1879"}}