{"id":"99cac76c3bdc","slug":"floating-down-the-river-99cac76c3bdc","title":"Floating Down The River.","content":"    My little bark glides steadily along,\r\n        Still and unshaken as a summer dream;\r\n        And never falls the oar into the stream,\r\n    For 'tis but morning, and the current strong;\r\n        So let the ripples bear me as they will;\r\n    Sweet, sweet is Life, and every sound is song;\r\n        Sorrow lies sleeping, and Joy sends me still\r\n                Swift floating down the River.\n\r\n    Bright shines the sun athwart the linden-trees;\r\n        One little cloud alone steals o'er the sky,\r\n        As o'er the widening stream below steal I,\r\n    Fann'd by the same faint perfume-laden breeze;\r\n        Bird-music answers sweetly through the air,\r\n    The unheard warbling of heart melodies;\r\n        Thus go I dreaming, free from faintest care,\r\n                Swift floating down the River.\n\r\n    Pure lie the broad-leaved lilies on the tide,\r\n        With glowing petals in the midst, that rest\r\n        Like the gold shower on Danae's lovely breast;\r\n    And the tall rushes cluster on the side.\r\n        Ho! sweet-lipp'd lily, thou must be my prize--\r\n    Thus shall I pluck thee in thy beauty's pride!\r\n        Fail'd--all too steadily my shallop hies,\r\n                Swift floating down the River.\n\r\n    The stream fast widens, and upon the shore\r\n        Rise busy hamlets 'mid the falling woods,\r\n        Filling their shorn and broken solitudes,\r\n    With labour's clamour ever more and more:\r\n        No more, no more in dreams of love all day,\r\n    Rich set in music from the forests hoar,\r\n        Now gaily speeds my untoss'd bark away,\r\n                Swift floating down the River.\n\r\n    Let me take oar, and turn mine eager prow,\r\n        Back to the quiet waveless source again,\r\n    Where no harsh sound breaks on the dreaming brain,\r\n    And winds steal softly round the careless brow,--\r\n        Swift as a dream my tiny bark hath gone,\r\n    And stoutly though I ply the oar, yet now\r\n        My weary shallop still goes sadly on,\r\n                Swift floating down the River.\n\r\n    Ah! never more for me--Ah! never more\r\n        Return those blessed morning hours again;\r\n        The sun beats hotly on my throbbing brain,\r\n    And no cool shade waves friendly from the shore:\r\n        My feeble oar dips powerless utterly,\r\n    And onward, onward, though I struggle sore,\r\n        Still goes my bark towards the surging sea,\r\n                Swift floating down the River.\n\r\n    Welcome art thou, O cool and fragrant eve!\r\n        Welcome art thou, though night pursue thee fast\r\n        With thee the burning and the toil roll past,\r\n    And there is time to gaze back and to grieve.\r\n        Hoarse ocean-murmurs fall upon mine ears,\r\n    And round me now prophetic billows heave,\r\n        As on I go, out-looking through salt tears,\r\n                Swift floating down the River,\r\n                Swift floating to the Sea.","writer":"Walter R. Cassels","category":["classic"],"meaning":"Walter R. Cassels's contribution to classic is further solidified by the brilliance found in \"Floating Down The River.\"...\n\n### Why We Love This Line\nAt Linespedia, we believe that poetry is the ultimate sanctuary for the soul...","meta":{"views":1358,"dates":"4 September 1826 - 10 June 1907"}}