{"id":"a0f4fe60b22f","slug":"to-a-boy-poet-of-the-decadence-a0f4fe60b22f","title":"To A Boy-Poet Of The Decadence","content":"\r\n[Showing curious reversal of epigram, 'La nature l'a fait sanglier; la civilisation l'a reduit a l'etat de cochon.']\n\n\r\n    But my good little man, you have made a mistake\r\n        If you really are pleased to suppose\r\n    That the Thames is alight with the lyrics you make;\r\n        We could all do the same if we chose.\n\r\n    From Solomon down, we may read, as we run,\r\n        Of the ways of a man and a maid;\r\n    There is nothing that's new to us under the sun,\r\n        And certainly not in the shade.\n\r\n    The erotic affairs that you fiddle aloud\r\n        Are as vulgar as coin of the mint;\r\n    And you merely distinguish yourself from the crowd\r\n        By the fact that you put 'em in print.\n\r\n    You're a 'prentice, my boy, in the primitive stage,\r\n        And you itch, like a boy, to confess:\r\n    When you know a bit more of the arts of the age\r\n        You will probably talk a bit less.\n\r\n    For your dull little vices we don't care a fig,\r\n        It is this that we deeply deplore;\r\n    You were cast for a common or usual pig,\r\n        But you play the invincible bore.","writer":"Owen Seaman","category":["classic"],"meaning":"Exploring the themes of classic, Owen Seaman delivers a powerful performance in \"To A Boy-Poet Of The Decadence\"...\n\n### Why We Love This Line\nAt Linespedia, we believe that poetry is the ultimate sanctuary for the soul...","meta":{"views":579,"dates":"18 September 1861 - 2 February 1936"}}