{"id":"aea6b95d784c","slug":"upon-comely-a-good-speaker-but-an-ill-singer-epig-aea6b95d784c","title":"Upon Comely, A Good Speaker But An Ill Singer. Epig.","content":"    Comely acts well; and when he speaks his part,\r\n    He doth it with the sweetest tones of art:\r\n    But when he sings a psalm, there's none can be\r\n    More curs'd for singing out of tune than he.","writer":"Robert Herrick","category":["classic"],"meaning":"Exploring the themes of classic, Robert Herrick delivers a powerful performance in \"Upon Comely, A Good Speaker But An Ill Singer. Epig.\"...\n\n### Why We Love This Line\nAt Linespedia, we believe that poetry is the ultimate sanctuary for the soul...","meta":{"views":1121,"dates":"Baptized - August 24, 1591- October 1674"}}