{"id":"ba27b3a23f98","slug":"the-rendezvous-ba27b3a23f98","title":"The Rendezvous","content":"    He faints with hope and fear. It is the hour.\r\n     Distant, across the thundering organ-swell,\r\n    In sweet discord from the cathedral-tower,\r\n     Fall the faint chimes and the thrice-sequent bell.\r\n    Over the crowd his eye uneasy roves.\r\n     He sees a plume, a fur; his heart dilates - \r\n    Soars . . . and then sinks again. It is not hers he loves.\r\n     She will not come, the woman that he waits.\n\r\n    Braided with streams of silver incense rise\r\n     The antique prayers and ponderous antiphones.\r\n    'Gloria Patri' echoes to the skies;\r\n     'Nunc et in saecula' the choir intones.\r\n    He marks not the monotonous refrain,\r\n     The priest that serves nor him that celebrates,\r\n    But ever scans the aisle for his blonde head. . . . In vain!\r\n     She will not come, the woman that he waits.\n\r\n    How like a flower seemed the perfumed place\r\n     Where the sweet flesh lay loveliest to kiss;\r\n    And her white hands in what delicious ways,\r\n     With what unfeigned caresses, answered his!\r\n    Each tender charm intolerable to lose,\r\n     Each happy scene his fancy recreates.\r\n    And he calls out her name and spreads his arms . . . No use!\r\n     She will not come, the woman that he waits.\n\r\n    But the long vespers close. The priest on high\r\n     Raises the thing that Christ's own flesh enforms;\r\n    And down the Gothic nave the crowd flows by\r\n     And through the portal's carven entry swarms.\r\n    Maddened he peers upon each passing face\r\n     Till the long drab procession terminates.\r\n    No princess passes out with proud majestic pace.\r\n     She has not come, the woman that he waits.\n\r\n    Back in the empty silent church alone\r\n     He walks with aching heart. A white-robed boy\r\n    Puts out the altar-candles one by one,\r\n     Even as by inches darkens all his joy.\r\n    He dreams of the sweet night their lips first met,\r\n     And groans - and turns to leave - and hesitates . . .\r\n    Poor stricken heart, he will, he can not fancy yet\r\n     She will not come, the woman that he waits.\n\r\n    But in an arch where deepest shadows fall\r\n     He sits and studies the old, storied panes,\r\n    And the calm crucifix that from the wall\r\n     Looks on a world that quavers and complains.\r\n    Hopeless, abandoned, desolate, aghast,\r\n     On modes of violent death he meditates.\r\n    And the tower-clock tolls five, and he admits at last,\r\n     She will not come, the woman that he waits.\n\r\n    Through the stained rose the winter daylight dies,\r\n     And all the tide of anguish unrepressed\r\n    Swells in his throat and gathers in his eyes;\r\n     He kneels and bows his head upon his breast,\r\n    And feigns a prayer to hide his burning tears,\r\n     While the satanic voice reiterates\r\n    'Tonight, tomorrow, nay, nor all the impending years,\r\n     She will not come,' the woman that he waits.\n\r\n    Fond, fervent heart of life's enamored spring,\r\n     So true, so confident, so passing fair,\r\n    That thought of Love as some sweet, tender thing,\r\n     And not as war, red tooth and nail laid bare,\r\n    How in that hour its innocence was slain,\r\n     How from that hour our disillusion dates,\r\n    When first we learned thy sense, ironical refrain,\r\n     She will not come, the woman that he waits.","writer":"Alan Seeger","category":["classic"],"meaning":"\"The Rendezvous\" is a quintessential example of Alan Seeger's signature style...\n\n### Why We Love This Line\nAt Linespedia, we believe that poetry is the ultimate sanctuary for the soul...","meta":{"views":1442,"dates":"June 22, 1888 - July 4, 1916"}}