{"id":"bb5292ca07d6","slug":"indian-summer-bb5292ca07d6","title":"Indian Summer","content":"    The dawn is a warp of fever,\r\n    The eve is a woof of fire;\r\n    And the month is a singing weaver\r\n    Weaving a red desire.\n\r\n    With stars Dawn dices with Even\r\n    For the rosy gold they heap\r\n    On the blue of the day's deep heaven,\r\n    On the black of the night's far deep.\n\r\n    It's 'Reins to the blood!' and 'Marry!'\r\n    The season's a prince who burns\r\n    With the teasing lusts that harry\r\n    His heart for a wench who spurns.\n\r\n    It's 'Crown us a beaker with sherry,\r\n    To drink to the doxy's heels;\r\n    A tankard of wine o' the berry,\r\n    To lips like a cloven peel's.\n\r\n    ' 'S death! if a king be saddened,\r\n    Right so let a fool laugh lies:\r\n    But wine! when a king is gladdened,\r\n    And a woman's waist and her eyes.'\n\r\n    He hath shattered the loom of the weaver,\r\n    And left but a leaf that flits,\r\n    He hath seized heaven's gold, and a fever\r\n    Of mist and of frost is its.\n\r\n    He hath tippled the buxom beauty,\r\n    And gotten her hug and her kiss\r\n    The wide world's royal booty\r\n    To pile at her feet for this.","writer":"Madison Julius Cawein","category":["classic"],"meaning":"\"Indian Summer\" is a quintessential example of Madison Julius Cawein's signature style...\n\n### Why We Love This Line\nAt Linespedia, we believe that poetry is the ultimate sanctuary for the soul...","meta":{"views":1341,"dates":"23 March 1865 - 8 December 1914"}}