{"id":"c412b1fafa15","slug":"a-good-woman-c412b1fafa15","title":"A Good Woman.","content":"        Her eyes are the windows of a soul\r\n         Where only the white thoughts spring,\r\n        And they look, as the eyes of the angels look,\r\n         For the good in everything.\n\r\n        Her lips can whisper the tenderest words\r\n         That weary and worn can hear,\r\n        Can tell of the dawn of a better morn\r\n         Till only the cowards fear.\n\r\n        Her hands can lift up the fallen one\r\n         From an overthrow complete,\r\n        Can take a soul from the mire of sin\r\n         And lead it to Christ's dear feet.\n\r\n        And she can walk wherever she will - \r\n         She walketh never alone.\r\n        The work she does is the Master's work,\r\n         And God guards well His own.","writer":"Jean Blewett","category":["classic"],"meaning":"Exploring the themes of classic, Jean Blewett delivers a powerful performance in \"A Good Woman.\"...\n\n### Why We Love This Line\nAt Linespedia, we believe that poetry is the ultimate sanctuary for the soul...","meta":{"views":1126,"dates":"1862 - 1934"}}