{"id":"ca6d78c096ab","slug":"nursery-rhyme-ccccli-love-and-matrimony-ca6d78c096ab","title":"Nursery Rhyme. CCCCLI. Love And Matrimony.","content":"                Little Jack Jingle,\r\n                He used to live single:\r\n        But when he got tired of this kind of life,\r\n        He left off being single, and liv'd with his wife.","writer":"Unknown","category":["classic"],"meaning":"\"Nursery Rhyme. CCCCLI. Love And Matrimony.\" is a quintessential example of Unknown's signature style...\n\n### Why We Love This Line\nAt Linespedia, we believe that poetry is the ultimate sanctuary for the soul...","meta":{"views":1388,"dates":null}}