{"id":"cb1221d692cb","slug":"the-broken-heart-cb1221d692cb","title":"The Broken Heart.","content":"    Oh think not with love's soft token,\r\n    Or music my heart to thrill \r\n    For its strings its strings are broken,\r\n    And the chords would fain be still!\n\r\n    Oh think not to waken the measure\r\n    Of joy on a ruined lute \r\n    Think not to waken pleasure,\r\n    Where grief sits mourning and mute.\n\r\n    The pearls that gleam in the billow,\r\n    But darken the gloom of the deep \r\n    And laughter plants the pillow\r\n    With thorns, where sorrow would sleep.\n\r\n    The gems that gleam on the finger\r\n    Of her who is sleeping and cold,\r\n    But wring the hearts that linger.\r\n    And dream of the love they told.\n\r\n    My bosom is but a grave,\r\n    My breast a voiceless choir \r\n    Speak not to the echoless cave,\r\n    Touch not the broken lyre!","writer":"Samuel Griswold Goodrich","category":["classic"],"meaning":"This evocative piece by Samuel Griswold Goodrich, titled \"The Broken Heart.\", represents a masterful exploration of classic. The lines capture a profound emotional resonance...\n\n### Why We Love This Line\nAt Linespedia, we believe that poetry is the ultimate sanctuary for the soul...","meta":{"views":1285,"dates":"August 19, 1793 - May 9, 1860"}}