{"id":"ce69808dcfd4","slug":"young-love-postscript-ce69808dcfd4","title":"Young Love Postscript","content":"So sang young Love in high and holy dream\nOf a white Love that hath no earthly taint,\nSo rapt within his vision he did seem\nLess like a boyish singer than a saint.\nAh, Boy, it is a dream for life too high,\nIt is a bird that hath no feet for earth:\nStrange wings, strange eyes, go seek another sky\nAnd find thy fellows of an equal birth.\nFor many a body-sweet material thing,\nWhat canst thou give us half so dear as these?\nWe would not soar amid the stars to sing,\nWarm and content amid the nested trees.\nYoung Seraph, go and lake thy song to heaven,\nWe would not grow unhappy with our lot,\nLeave us the simple love the earth hath given -\nSing where thou wilt, so that we hear thee not.","writer":"Richard Le Gallienne","category":["classical-poetry"],"meaning":"This evocative piece by Richard Le Gallienne, titled \"Young Love Postscript\", represents a masterful exploration of classical-poetry. The lines capture a profound emotional resonance...\n\n### Why We Love This Line\nAt Linespedia, we believe that poetry is the ultimate sanctuary for the soul...","meta":{"source":"public-domain-poetry"}}