{"id":"ce764e08dde2","slug":"the-family-burying-ground-ce764e08dde2","title":"The Family Burying-Ground.","content":"    A wall of crumbling stones doth keep\r\n    Watch o'er long barrows where they sleep,\r\n     Old chronicled grave-stones of its dead,\r\n    On which oblivious mosses creep\r\n     And lichens gray as lead.\n\r\n    Warm days the lost cows as they pass\r\n    Rest here and browse the juicy grass\r\n     That springs about its sun-scorched stones;\r\n    Afar one hears their bells' deep brass\r\n     Waft melancholy tones.\n\r\n    Here the wild morning-glory goes\r\n    A-rambling as the myrtle grows,\r\n     Wild morning-glories pale as pain,\r\n    With holy urns, that hint at woes,\r\n     The night hath filled with rain.\n\r\n    Here are blackberries largest seen,\r\n    Rich, winey dark, whereon the lean\r\n     Black hornet sucks, noons sick with heat,\r\n    That bend not to the shadowed green\r\n     The heavy bearded wheat.\n\r\n    At dark, for its forgotten dead,\r\n    A requiem, of no known wind said,\r\n     Through ghostly cedars moans and throbs,\r\n    While to thin starlight overhead\r\n     The shivering screech-owl sobs.\n\n","writer":"Madison Julius Cawein","category":["classic"],"meaning":"This evocative piece by Madison Julius Cawein, titled \"The Family Burying-Ground.\", represents a masterful exploration of classic. The lines capture a profound emotional resonance...\n\n### Why We Love This Line\nAt Linespedia, we believe that poetry is the ultimate sanctuary for the soul...","meta":{"views":926,"dates":"23 March 1865 - 8 December 1914"}}