{"id":"e24cf27b242c","slug":"silence-e24cf27b242c","title":"Silence.","content":"    I am the word that lovers leave unsaid,\r\n        The eloquence of ardent lips grown mute,\r\n    The mourning mother's heart-cry for her dead,\r\n        The flower of faith that grows to unseen fruit.\n\r\n    I am the speech of prophets when their eyes\r\n        Behold some splendid vision of the soul;\r\n    The song of morning stars, the hills' replies,\r\n        The far call of the immaterial pole.\n\r\n    And, since I must be mateless, I shall win\r\n        One boon beyond the meed of common clay:\r\n    My life shall end where other lives begin,\r\n        And live when other lives have passed away.","writer":"Charles Hamilton Musgrove","category":["classic"],"meaning":"\"Silence.\" is a quintessential example of Charles Hamilton Musgrove's signature style...\n\n### Why We Love This Line\nAt Linespedia, we believe that poetry is the ultimate sanctuary for the soul...","meta":{"views":1230,"dates":null}}