{"id":"fa3cef43ea84","slug":"tears-fa3cef43ea84","title":"Tears","content":"    The tears that trickled down our eyes,\r\n     They do not touch the earth to-day;\r\n    But soar like angels to the skies,\r\n     And, like the angels, may not die;\r\n        For ah! our immortality\r\n        Flows thro' each tear -- sounds in each sigh.\n\r\n    What waves of tears surge o'er the deep\r\n     Of sorrow in our restless souls!\r\n    And they are strong, not weak, who weep\r\n     Those drops from out the sea that rolls\r\n        Within their hearts forevermore,\r\n        Without a depth -- without a shore.\n\r\n    But ah! the tears that are not wept,\r\n     The tears that never outward fall;\r\n    The tears that grief for years has kept\r\n     Within us -- they are best of all;\r\n        The tears our eyes shall never know,\r\n        Are dearer than the tears that flow.\n\r\n    Each night upon earth's flowers below,\r\n     The dew comes down from darkest skies,\r\n    And every night our tears of woe\r\n     Go up like dews to Paradise,\r\n        To keep in bloom, and make more fair,\r\n        The flowers of crowns we yet shall wear.\n\r\n    For ah! the surest way to God\r\n     Is up the lonely streams of tears,\r\n    That flow when bending 'neath His rod,\r\n     And fill the tide of earthly years.\r\n        On laughter's billows hearts are tossed,\r\n        On waves of tears no heart is lost.\n\r\n    Flow on, ye tears! and bear me home;\r\n     Flow not! ye tears of deeper woe;\r\n    Flow on, ye tears! that are but foam\r\n     Of deeper waves that will not flow.\r\n        A little while -- I reach the shore\r\n        Where tears flow not forevermore!","writer":"Abram Joseph Ryan","category":["classic"],"meaning":"Abram Joseph Ryan's contribution to classic is further solidified by the brilliance found in \"Tears\"...\n\n### Why We Love This Line\nAt Linespedia, we believe that poetry is the ultimate sanctuary for the soul...","meta":{"views":1515,"dates":"August 15, 1839 - April 22, 1886"}}