{"id":"fb91c1ac2229","slug":"nursery-rhyme-lxxv-tales-fb91c1ac2229","title":"Nursery Rhyme. LXXV. Tales.","content":"            [The tale of Jack Horner has long been appropriated to the nursery. The four lines which follow are the traditional ones, and they form part of 'The pleasant History of Jack Horner, containing his witty Tricks and pleasant Pranks, which he plaied from his Youth to his riper Years,' 12mo, a copy of which is in the Bodleian Library, and this extended story is in substance the same with 'The Fryer and the Boy,' 12mo, Lond. 1617, and both of them are taken from the more ancient story of 'Jack and his Step-dame,' which has been printed by Mr. Wright.]\n\r\n        Little Jack Horner sat in the corner,\r\n            Eating a Christmas pie;\r\n        He put in his thumb, and he took out a plum,\r\n            And said, \"What a good boy am I!\"","writer":"Unknown","category":["classic"],"meaning":"Unknown's contribution to classic is further solidified by the brilliance found in \"Nursery Rhyme. LXXV. Tales.\"...\n\n### Why We Love This Line\nAt Linespedia, we believe that poetry is the ultimate sanctuary for the soul...","meta":{"views":1060,"dates":null}}