[
  {
    "title": "The Void",
    "writer": "kevin",
    "slug": "the-void",
    "url": "https://allpoetry.com/poem/1-The-Void-by-kevin"
  },
  {
    "title": "eyespark",
    "writer": "kevin",
    "slug": "eyespark",
    "url": "https://allpoetry.com/poem/3-eyespark-by-kevin"
  },
  {
    "title": "Definition of love",
    "writer": "kevin",
    "slug": "definition-of-love",
    "url": "https://allpoetry.com/poem/4-Definition-of-love-by-kevin"
  },
  {
    "title": "lonely grave",
    "writer": "kevin",
    "slug": "lonely-grave",
    "url": "https://allpoetry.com/poem/5-lonely-grave-by-kevin"
  },
  {
    "title": "alone in the rain",
    "writer": "kevin",
    "slug": "alone-in-the-rain",
    "url": "https://allpoetry.com/poem/6-alone-in-the-rain-by-kevin"
  },
  {
    "title": "lead phone",
    "writer": "kevin",
    "slug": "lead-phone",
    "url": "https://allpoetry.com/poem/7-lead-phone-by-kevin"
  },
  {
    "title": "winter's first spring",
    "writer": "kevin",
    "slug": "winters-first-spring",
    "url": "https://allpoetry.com/poem/9-winters-first-spring-by-kevin"
  },
  {
    "title": "blissful shall the children find us",
    "writer": "kevin",
    "slug": "blissful-shall-the-children-find-us",
    "url": "https://allpoetry.com/poem/10-blissful-shall-the-children-find-us-by-kevin"
  },
  {
    "title": "murkiness",
    "writer": "kevin",
    "slug": "murkiness",
    "url": "https://allpoetry.com/poem/12-murkiness-by-kevin"
  },
  {
    "title": "dancing",
    "writer": "kevin",
    "slug": "dancing",
    "url": "https://allpoetry.com/poem/13-dancing-by-kevin"
  },
  {
    "title": "two northwesterners",
    "writer": "kevin",
    "slug": "two-northwesterners",
    "url": "https://allpoetry.com/poem/14-two-northwesterners-by-kevin"
  },
  {
    "title": "winter indoors",
    "writer": "kevin",
    "slug": "winter-indoors",
    "url": "https://allpoetry.com/poem/15-winter-indoors-by-kevin"
  },
  {
    "title": "my moon",
    "writer": "kevin",
    "slug": "my-moon",
    "url": "https://allpoetry.com/poem/16-my-moon-by-kevin"
  },
  {
    "title": "both so young",
    "writer": "kevin",
    "slug": "both-so-young",
    "url": "https://allpoetry.com/poem/17-both-so-young-by-kevin"
  },
  {
    "title": "moment of decision",
    "writer": "kevin",
    "slug": "moment-of-decision",
    "url": "https://allpoetry.com/poem/18-moment-of-decision-by-kevin"
  },
  {
    "title": "standing and leaning",
    "writer": "kevin",
    "slug": "standing-and-leaning",
    "url": "https://allpoetry.com/poem/20-standing-and-leaning-by-kevin"
  },
  {
    "title": "greenroad to red",
    "writer": "kevin",
    "slug": "greenroad-to-red",
    "url": "https://allpoetry.com/poem/21-greenroad-to-red-by-kevin"
  },
  {
    "title": "bad habit!",
    "writer": "kevin",
    "slug": "bad-habit",
    "url": "https://allpoetry.com/poem/22-bad-habit--by-kevin"
  },
  {
    "title": "Fear Way out Taking a Loss",
    "writer": "Francisco Larios",
    "slug": "fear-way-out-taking-a-loss",
    "url": "https://allpoetry.com/poem/24-Fear-Way-out-Taking-a-Loss-by-Francisco-Larios"
  },
  {
    "title": "taking a loss",
    "writer": "Francisco Larios",
    "slug": "taking-a-loss",
    "url": "https://allpoetry.com/poem/25-taking-a-loss-by-Francisco-Larios"
  },
  {
    "title": "Way out",
    "writer": "Francisco Larios",
    "slug": "way-out",
    "url": "https://allpoetry.com/poem/26-Way-out-by-Francisco-Larios"
  },
  {
    "title": "Alone",
    "writer": "Arabian Knight",
    "slug": "alone",
    "url": "https://allpoetry.com/poem/32-Alone-by-Arabian-Knight"
  },
  {
    "title": "I'll Think Of You Forever",
    "writer": "Arabian Knight",
    "slug": "ill-think-of-you-forever",
    "url": "https://allpoetry.com/poem/33-Ill-Think-Of-You-Forever-by-Arabian-Knight"
  },
  {
    "title": "Deduction",
    "writer": "Isaac",
    "slug": "deduction",
    "url": "https://allpoetry.com/poem/35-Deduction-by-Isaac"
  },
  {
    "title": "Cape Argo",
    "writer": "Ben Kerensa",
    "slug": "cape-argo",
    "url": "https://allpoetry.com/poem/37-Cape-Argo-by-Ben-Kerensa"
  },
  {
    "title": "Better things in life",
    "writer": "Isaac",
    "slug": "better-things-in-life",
    "url": "https://allpoetry.com/poem/42-Better-things-in-life-by-Isaac"
  },
  {
    "title": "Yesterday",
    "writer": "Josh Williams",
    "slug": "yesterday",
    "url": "https://allpoetry.com/poem/44-Yesterday-by-Josh-Williams"
  },
  {
    "title": "Why the Strong Man Cries",
    "writer": "Josh Williams",
    "slug": "why-the-strong-man-cries",
    "url": "https://allpoetry.com/poem/45--Why-the-Strong-Man-Cries-by-Josh-Williams"
  },
  {
    "title": "You and Me",
    "writer": "Josh Williams",
    "slug": "you-and-me",
    "url": "https://allpoetry.com/poem/46-You-and-Me-by-Josh-Williams"
  },
  {
    "title": "I love you",
    "writer": "Anonymous Poet",
    "slug": "i-love-you",
    "url": "https://allpoetry.com/poem/52-I-love-you-by-Anonymous-Poet"
  },
  {
    "title": "Chamber Of Creation",
    "writer": "Nathan Owens",
    "slug": "chamber-of-creation",
    "url": "https://allpoetry.com/poem/53-Chamber-Of-Creation-by-Nathan-Owens"
  },
  {
    "title": "What!?!?!?",
    "writer": "Nathan Owens",
    "slug": "what",
    "url": "https://allpoetry.com/poem/54-What-------by-Nathan-Owens"
  },
  {
    "title": "Decay Of Your Time",
    "writer": "Nathan Owens",
    "slug": "decay-of-your-time",
    "url": "https://allpoetry.com/poem/55-Decay-Of-Your-Time-by-Nathan-Owens"
  },
  {
    "title": "Devilish",
    "writer": "Nathan Owens",
    "slug": "devilish",
    "url": "https://allpoetry.com/poem/56-Devilish-by-Nathan-Owens"
  },
  {
    "title": "In the Hourglass",
    "writer": "Nathan Owens",
    "slug": "in-the-hourglass",
    "url": "https://allpoetry.com/poem/57-In-the-Hourglass-by-Nathan-Owens"
  },
  {
    "title": "Living Inside Myself",
    "writer": "Nathan Owens",
    "slug": "living-inside-myself",
    "url": "https://allpoetry.com/poem/58-Living-Inside-Myself-by-Nathan-Owens"
  },
  {
    "title": "Lovers of the Night",
    "writer": "Nathan Owens",
    "slug": "lovers-of-the-night",
    "url": "https://allpoetry.com/poem/59-Lovers-of-the-Night-by-Nathan-Owens"
  },
  {
    "title": "Tightly Held Dreaming",
    "writer": "Nathan Owens",
    "slug": "tightly-held-dreaming",
    "url": "https://allpoetry.com/poem/60-Tightly-Held-Dreaming-by-Nathan-Owens"
  },
  {
    "title": "Goodbye my long lost love",
    "writer": "Richard Davis",
    "slug": "goodbye-my-long-lost-love",
    "url": "https://allpoetry.com/poem/61-Goodbye-my-long-lost-love-by-Richard-Davis"
  },
  {
    "title": "Soulmates",
    "writer": "Richard Davis",
    "slug": "soulmates",
    "url": "https://allpoetry.com/poem/62-Soulmates-by-Richard-Davis"
  },
  {
    "title": "What is love? a poem to my Paigey",
    "writer": "Richard Davis",
    "slug": "what-is-love-a-poem-to-my-paigey",
    "url": "https://allpoetry.com/poem/63-What-is-love--a-poem-to-my-Paigey-by-Richard-Davis"
  },
  {
    "title": "Dreams Of Me",
    "writer": "Tony Pacheco",
    "slug": "dreams-of-me",
    "url": "https://allpoetry.com/poem/72-Dreams-Of-Me-by-Tony-Pacheco"
  },
  {
    "title": "Don't Come Home",
    "writer": "Tony Pacheco",
    "slug": "dont-come-home",
    "url": "https://allpoetry.com/poem/73-Dont-Come-Home-by-Tony-Pacheco"
  },
  {
    "title": "Last Time Around",
    "writer": "Tony Pacheco",
    "slug": "last-time-around",
    "url": "https://allpoetry.com/poem/74-Last-Time-Around-by-Tony-Pacheco"
  },
  {
    "title": "Leave The Stars To Me",
    "writer": "Tony Pacheco",
    "slug": "leave-the-stars-to-me",
    "url": "https://allpoetry.com/poem/75-Leave-The-Stars-To-Me-by-Tony-Pacheco"
  },
  {
    "title": "Shadows Of Summer",
    "writer": "Tony Pacheco",
    "slug": "shadows-of-summer",
    "url": "https://allpoetry.com/poem/76-Shadows-Of-Summer-by-Tony-Pacheco"
  },
  {
    "title": "Somethings Never Change",
    "writer": "Tony Pacheco",
    "slug": "somethings-never-change",
    "url": "https://allpoetry.com/poem/77-Somethings-Never-Change-by-Tony-Pacheco"
  },
  {
    "title": "Thanks For Everything",
    "writer": "Tony Pacheco",
    "slug": "thanks-for-everything",
    "url": "https://allpoetry.com/poem/78-Thanks-For-Everything-by-Tony-Pacheco"
  },
  {
    "title": "The Last Summer",
    "writer": "Tony Pacheco",
    "slug": "the-last-summer",
    "url": "https://allpoetry.com/poem/79-The-Last-Summer-by-Tony-Pacheco"
  },
  {
    "title": "Thoughts Have Wings",
    "writer": "Tony Pacheco",
    "slug": "thoughts-have-wings",
    "url": "https://allpoetry.com/poem/80-Thoughts-Have-Wings-by-Tony-Pacheco"
  },
  {
    "title": "Untitled",
    "writer": "Tony Pacheco",
    "slug": "untitled",
    "url": "https://allpoetry.com/poem/81-Untitled-by-Tony-Pacheco"
  },
  {
    "title": "Kill the Children",
    "writer": "david",
    "slug": "kill-the-children",
    "url": "https://allpoetry.com/poem/83-Kill-the-Children-by-david"
  },
  {
    "title": "be ready too",
    "writer": "kevin",
    "slug": "be-ready-too",
    "url": "https://allpoetry.com/poem/84-be-ready-too-by-kevin"
  },
  {
    "title": "wHiTe LiEs",
    "writer": "nine",
    "slug": "white-lies",
    "url": "https://allpoetry.com/poem/89-wHiTe-LiEs-by-nine"
  },
  {
    "title": "I mIsS yOu",
    "writer": "nine",
    "slug": "i-miss-you",
    "url": "https://allpoetry.com/poem/90-I-mIsS-yOu-by-nine"
  },
  {
    "title": "sOmEtImEs SoMeThInGs",
    "writer": "nine",
    "slug": "sometimes-somethings",
    "url": "https://allpoetry.com/poem/91-sOmEtImEs-SoMeThInGs-by-nine"
  },
  {
    "title": "[I want to curl up in a little ball]",
    "writer": "Lightmare",
    "slug": "i-want-to-curl-up-in-a-little-ball",
    "url": "https://allpoetry.com/poem/98-I-want-to-curl-up-in-a-little-ball-by-Lightmare"
  },
  {
    "title": "Don’t Shed a Tear for Me",
    "writer": "Lightmare",
    "slug": "dont-shed-a-tear-for-me",
    "url": "https://allpoetry.com/poem/99-Don-t-Shed-a-Tear-for-Me-by-Lightmare"
  },
  {
    "title": "[Pale golden wings beat against the cool air]",
    "writer": "Lightmare",
    "slug": "pale-golden-wings-beat-against-the-cool-air",
    "url": "https://allpoetry.com/poem/100-Pale-golden-wings-beat-against-the-cool-air-by-Lightmare"
  },
  {
    "title": "Telepathic Foodstuff",
    "writer": "Isaac",
    "slug": "telepathic-foodstuff",
    "url": "https://allpoetry.com/poem/101-Telepathic-Foodstuff-by-Isaac"
  },
  {
    "title": "Butterfly",
    "writer": "Isaac",
    "slug": "butterfly",
    "url": "https://allpoetry.com/poem/102-Butterfly-by-Isaac"
  },
  {
    "title": "The First Inquiry",
    "writer": "Arabian Knight",
    "slug": "the-first-inquiry",
    "url": "https://allpoetry.com/poem/104-The-First-Inquiry-by-Arabian-Knight"
  },
  {
    "title": "The Court Of Love",
    "writer": "Arabian Knight",
    "slug": "the-court-of-love",
    "url": "https://allpoetry.com/poem/105-The-Court-Of-Love-by-Arabian-Knight"
  }
]